bannerbear_mcp/__init__.py
bannerbear_mcp/schema.json
bannerbear_mcp/server.py
bannerbear_mcp-0.1.0.dist-info/LICENSE
bannerbear_mcp-0.1.0.dist-info/METADATA
bannerbear_mcp-0.1.0.dist-info/WHEEL
bannerbear_mcp-0.1.0.dist-info/entry_points.txt
bannerbear_mcp-0.1.0.dist-info/RECORD
