Metadata-Version: 2.3
Name: bannerbear-mcp
Version: 0.1.0
Summary: A MCP Server for Bannerbear, built on top of FastMCP.
License: MIT
Author: yanrujing
Author-email: rujing.yan@protagonist-ai.com
Requires-Python: >=3.11,<4.0
Classifier: License :: OSI Approved :: MIT License
Classifier: Programming Language :: Python :: 3
Classifier: Programming Language :: Python :: 3.11
Classifier: Programming Language :: Python :: 3.12
Classifier: Programming Language :: Python :: 3.13
Requires-Dist: fastmcp (>=2.11.3,<3.0.0)
